bonobo_trans/__init__.py
bonobo_trans/aggregator.py
bonobo_trans/logging.py
bonobo_trans/lookup.py
bonobo_trans/sequencer.py
bonobo_trans/sorter.py
bonobo_trans/source.py
bonobo_trans/target.py
bonobo_trans-0.0.4.dist-info/LICENSE.txt
bonobo_trans-0.0.4.dist-info/METADATA
bonobo_trans-0.0.4.dist-info/WHEEL
bonobo_trans-0.0.4.dist-info/top_level.txt
bonobo_trans-0.0.4.dist-info/RECORD
